src/__init__.py
src/main.py
src/config/__init__.py
src/config/main.py
src/interfaces/__init__.py
src/interfaces/account.py
src/interfaces/ads.py
src/interfaces/attachments.py
src/interfaces/groups.py
src/interfaces/main.py
src/interfaces/photo.py
src/interfaces/video.py
src/interfaces/wall.py
src/service/__init__.py
src/service/main.py
connector_savarety-1.0.1.dist-info/LICENSE
connector_savarety-1.0.1.dist-info/METADATA
connector_savarety-1.0.1.dist-info/WHEEL
connector_savarety-1.0.1.dist-info/top_level.txt
connector_savarety-1.0.1.dist-info/RECORD
